CHANGES.rst
README.rst
requirements.txt
setup.py
doc/conf.py
doc/index.rst
doc/requirements.txt
doc/settings.rst
moderation/__init__.py
moderation/ajax.py
moderation/context_processors.py
moderation/models.py
moderation/urls.py
moderation/views.py
moderation/static/css/moderation.css
moderation/static/images/ajax-loader.gif
moderation/static/js/moderation.js
moderation/templates/moderation/base.html
moderation/templates/moderation/dashboard.html
moderation/templates/moderation/dialogs.html
moderation/templates/moderation/flagged.html
moderation/templates/moderation/flags.html
moderation/templates/moderation/pending.html
moderation/templates/moderation/spam.html
moderation/templates/moderation/assets/asset.html
moderation/templates/moderation/assets/bits/content.html
moderation/templates/moderation/assets/body/audio.html
moderation/templates/moderation/assets/body/base.html
moderation/templates/moderation/assets/body/comment.html
moderation/templates/moderation/assets/body/link.html
moderation/templates/moderation/assets/body/photo.html
moderation/templates/moderation/assets/body/post.html
moderation/templates/moderation/assets/body/video.html
moderation/templates/moderation/base/dialogs.html
moderation/templates/moderation/base/bits/moderate.html
moderation/templates/moderation/bits/moderate.html