Metadata-Version: 1.1
Name: typepadapp-moderation
Version: 1.0.3
Summary: Moderation panel for TypePad applications.
Home-page: http://github.com/sixapart/typepadapp-moderation/
Author: Six Apart
Author-email: python@sixapart.com
License: UNKNOWN
Platform: UNKNOWN
Requires: Django(>=1.1.1)
Requires: typepadapp(>=1.1.2)
Requires: akismet(>=0.2.0)
Provides: moderation
